Metadata-Version: 1.0
Name: yanhui-text2speech
Version: 0.1
Summary: Convert text to speech
Home-page: UNKNOWN
Author: yanhui 
Author-email: yanhui@csdn.net
License: UNKNOWN
Platform: UNKNOWN
